odoo/addons/product_pack/README.rst
odoo/addons/product_pack/__init__.py
odoo/addons/product_pack/__manifest__.py
odoo/addons/product_pack/demo/product_pack_line_demo.xml
odoo/addons/product_pack/demo/product_product_demo.xml
odoo/addons/product_pack/i18n/ca.po
odoo/addons/product_pack/i18n/es.po
odoo/addons/product_pack/i18n/es_AR.po
odoo/addons/product_pack/i18n/fr.po
odoo/addons/product_pack/i18n/it.po
odoo/addons/product_pack/i18n/nl.po
odoo/addons/product_pack/i18n/product_pack.pot
odoo/addons/product_pack/i18n/pt.po
odoo/addons/product_pack/i18n/sv.po
odoo/addons/product_pack/models/__init__.py
odoo/addons/product_pack/models/product_pack_line.py
odoo/addons/product_pack/models/product_pricelist.py
odoo/addons/product_pack/models/product_product.py
odoo/addons/product_pack/models/product_template.py
odoo/addons/product_pack/readme/CONTRIBUTORS.rst
odoo/addons/product_pack/readme/DESCRIPTION.rst
odoo/addons/product_pack/readme/ROADMAP.rst
odoo/addons/product_pack/readme/USAGE.rst
odoo/addons/product_pack/security/ir.model.access.csv
odoo/addons/product_pack/static/description/icon.png
odoo/addons/product_pack/static/description/index.html
odoo/addons/product_pack/tests/__init__.py
odoo/addons/product_pack/tests/common.py
odoo/addons/product_pack/tests/test_product_pack.py
odoo/addons/product_pack/views/product_pack_line_views.xml
odoo/addons/product_pack/views/product_product_views.xml
odoo/addons/product_pack/views/product_template_views.xml
odoo14_addon_product_pack-14.0.1.1.2.dist-info/METADATA
odoo14_addon_product_pack-14.0.1.1.2.dist-info/WHEEL
odoo14_addon_product_pack-14.0.1.1.2.dist-info/top_level.txt
odoo14_addon_product_pack-14.0.1.1.2.dist-info/RECORD
